<?xml version="1.0" encoding="UTF-8"?>
<channels>
  <channel site="dstv.com" lang="en" xmltv_id="" site_id="eri#102">M-Net East HD</channel>
  <channel site="dstv.com" lang="en" xmltv_id="" site_id="eri#103">1 Magic HD</channel>
  <channel site="dstv.com" lang="en" xmltv_id="" site_id="eri#104">M-Net Movies 1 East HD</channel>
  <channel site="dstv.com" lang="en" xmltv_id="" site_id="eri#106">M-Net Movies 2</channel>
  <channel site="dstv.com" lang="en" xmltv_id="" site_id="eri#107">M-Net Movies 3</channel>
  <channel site="dstv.com" lang="en" xmltv_id="" site_id="eri#108">M-Net Movies 4</channel>
  <channel site="dstv.com" lang="en" xmltv_id="" site_id="eri#112">Studio Universal HD</channel>
  <channel site="dstv.com" lang="en" xmltv_id="" site_id="eri#113">MovieRoom Africa</channel>
  <channel site="dstv.com" lang="en" xmltv_id="" site_id="eri#114">KIX</channel>
  <channel site="dstv.com" lang="en" xmltv_id="" site_id="eri#115">ME Channel</channel>
  <channel site="dstv.com" lang="en" xmltv_id="" site_id="eri#117">Universal TV</channel>
  <channel site="dstv.com" lang="en" xmltv_id="" site_id="eri#118">TeleMundo</channel>
  <channel site="dstv.com" lang="en" xmltv_id="" site_id="eri#120">BBC Brit</channel>
  <channel site="dstv.com" lang="en" xmltv_id="" site_id="eri#121">Discovery Channel HD</channel>
  <channel site="dstv.com" lang="en" xmltv_id="" site_id="eri#122">Comedy Central</channel>
  <channel site="dstv.com" lang="en" xmltv_id="" site_id="eri#124">E! Entertainment</channel>
  <channel site="dstv.com" lang="en" xmltv_id="" site_id="eri#128">WWE Channel</channel>
  <channel site="dstv.com" lang="en" xmltv_id="" site_id="eri#129">BET</channel>
  <channel site="dstv.com" lang="en" xmltv_id="" site_id="eri#130">MTV</channel>
  <channel site="dstv.com" lang="en" xmltv_id="" site_id="eri#132">CBS Reality</channel>
  <channel site="dstv.com" lang="en" xmltv_id="" site_id="eri#133">TLNovelas</channel>
  <channel site="dstv.com" lang="en" xmltv_id="" site_id="eri#135">Discovery TLC Entertainment</channel>
  <channel site="dstv.com" lang="en" xmltv_id="" site_id="eri#136">Discovery Family HD</channel>
  <channel site="dstv.com" lang="en" xmltv_id="" site_id="eri#137">TNT Africa</channel>
  <channel site="dstv.com" lang="en" xmltv_id="" site_id="eri#142">Pearl Magic Loko</channel>
  <channel site="dstv.com" lang="en" xmltv_id="" site_id="eri#151">Africa Magic Showcase HD</channel>
  <channel site="dstv.com" lang="en" xmltv_id="" site_id="eri#152">Africa Magic Epic</channel>
  <channel site="dstv.com" lang="en" xmltv_id="" site_id="eri#153">Africa Magic Urban</channel>
  <channel site="dstv.com" lang="en" xmltv_id="" site_id="eri#154">Africa Magic Family</channel>
  <channel site="dstv.com" lang="en" xmltv_id="" site_id="eri#155">Real Time</channel>
  <channel site="dstv.com" lang="en" xmltv_id="" site_id="eri#156">Africa Magic Hausa</channel>
  <channel site="dstv.com" lang="en" xmltv_id="" site_id="eri#157">Africa Magic Yoruba</channel>
  <channel site="dstv.com" lang="en" xmltv_id="" site_id="eri#159">Africa Magic Igbo</channel>
  <channel site="dstv.com" lang="en" xmltv_id="" site_id="eri#160">Maisha Magic Bongo</channel>
  <channel site="dstv.com" lang="en" xmltv_id="" site_id="eri#163">Maisha Magic Plus HD</channel>
  <channel site="dstv.com" lang="en" xmltv_id="" site_id="eri#166">Zee World</channel>
  <channel site="dstv.com" lang="en" xmltv_id="" site_id="eri#167">Star Life</channel>
  <channel site="dstv.com" lang="en" xmltv_id="" site_id="eri#168">ROK</channel>
  <channel site="dstv.com" lang="en" xmltv_id="" site_id="eri#169">ROK 2</channel>
  <channel site="dstv.com" lang="en" xmltv_id="" site_id="eri#170">CBS Justice</channel>
  <channel site="dstv.com" lang="en" xmltv_id="" site_id="eri#171">Investigation Discovery (ID)</channel>
  <channel site="dstv.com" lang="en" xmltv_id="" site_id="eri#174">BBC Lifestyle</channel>
  <channel site="dstv.com" lang="en" xmltv_id="" site_id="eri#175">Food Network</channel>
  <channel site="dstv.com" lang="en" xmltv_id="" site_id="eri#181">National Geographic Channel</channel>
  <channel site="dstv.com" lang="en" xmltv_id="" site_id="eri#183">Wild Earth</channel>
  <channel site="dstv.com" lang="en" xmltv_id="" site_id="eri#185">Curiosity Channel</channel>
  <channel site="dstv.com" lang="en" xmltv_id="" site_id="eri#186">The History Channel</channel>
  <channel site="dstv.com" lang="en" xmltv_id="" site_id="eri#190">Spice TV</channel>
  <channel site="dstv.com" lang="en" xmltv_id="" site_id="eri#194">Televista</channel>
  <channel site="dstv.com" lang="en" xmltv_id="" site_id="eri#195">Trybe</channel>
  <channel site="dstv.com" lang="en" xmltv_id="" site_id="eri#198">Holiday Channel</channel>
  <channel site="dstv.com" lang="en" xmltv_id="" site_id="eri#218">ESPN</channel>
  <channel site="dstv.com" lang="en" xmltv_id="" site_id="eri#219">ESPN 2 HD</channel>
  <channel site="dstv.com" lang="en" xmltv_id="" site_id="eri#220">SS Blitz Africa HD</channel>
  <channel site="dstv.com" lang="en" xmltv_id="" site_id="eri#221">SS Grandstand Africa</channel>
  <channel site="dstv.com" lang="en" xmltv_id="" site_id="eri#222">SS Football Plus Africa</channel>
  <channel site="dstv.com" lang="en" xmltv_id="" site_id="eri#223">SS Premier League Africa HD</channel>
  <channel site="dstv.com" lang="en" xmltv_id="" site_id="eri#224">SS LaLiga Africa HD</channel>
  <channel site="dstv.com" lang="en" xmltv_id="" site_id="eri#225">SS Football Africa</channel>
  <channel site="dstv.com" lang="en" xmltv_id="" site_id="eri#226">SS Variety 1 Africa</channel>
  <channel site="dstv.com" lang="en" xmltv_id="" site_id="eri#227">SS Variety 2 Africa HD</channel>
  <channel site="dstv.com" lang="en" xmltv_id="" site_id="eri#228">SS Variety 3 Africa</channel>
  <channel site="dstv.com" lang="en" xmltv_id="" site_id="eri#229">SS Variety 4 Africa</channel>
  <channel site="dstv.com" lang="en" xmltv_id="" site_id="eri#234">SS Tennis Africa</channel>
  <channel site="dstv.com" lang="en" xmltv_id="" site_id="eri#235">SS Motorsport Africa</channel>
  <channel site="dstv.com" lang="en" xmltv_id="" site_id="eri#241">SS Maximo 1 (P)</channel>
  <channel site="dstv.com" lang="en" xmltv_id="" site_id="eri#242">SS Maximo 2 (P)</channel>
  <channel site="dstv.com" lang="en" xmltv_id="" site_id="eri#275">K24</channel>
  <channel site="dstv.com" lang="en" xmltv_id="" site_id="eri#294">Cloud Plus</channel>
  <channel site="dstv.com" lang="en" xmltv_id="" site_id="eri#296">Wasafi TV</channel>
  <channel site="dstv.com" lang="en" xmltv_id="" site_id="eri#301">Cartoon Network</channel>
  <channel site="dstv.com" lang="en" xmltv_id="" site_id="eri#302">Cartoonito</channel>
  <channel site="dstv.com" lang="en" xmltv_id="" site_id="eri#303">Disney Channel</channel>
  <channel site="dstv.com" lang="en" xmltv_id="" site_id="eri#304">DreamWorks</channel>
  <channel site="dstv.com" lang="en" xmltv_id="" site_id="eri#305">Nickelodeon</channel>
  <channel site="dstv.com" lang="en" xmltv_id="" site_id="eri#307">NickJr</channel>
  <channel site="dstv.com" lang="en" xmltv_id="" site_id="eri#308">NickTOONS</channel>
  <channel site="dstv.com" lang="en" xmltv_id="" site_id="eri#309">Disney Junior</channel>
  <channel site="dstv.com" lang="en" xmltv_id="" site_id="eri#310">Jim Jam</channel>
  <channel site="dstv.com" lang="en" xmltv_id="" site_id="eri#313">PBS Kids</channel>
  <channel site="dstv.com" lang="en" xmltv_id="" site_id="eri#314">Moonbug</channel>
  <channel site="dstv.com" lang="en" xmltv_id="" site_id="eri#315">Teen Africa TV</channel>
  <channel site="dstv.com" lang="en" xmltv_id="" site_id="eri#319">Mindset</channel>
  <channel site="dstv.com" lang="en" xmltv_id="" site_id="eri#322">MTV base</channel>
  <channel site="dstv.com" lang="en" xmltv_id="" site_id="eri#323">TRACE Mziki</channel>
  <channel site="dstv.com" lang="en" xmltv_id="" site_id="eri#324">HIP TV</channel>
  <channel site="dstv.com" lang="en" xmltv_id="" site_id="eri#325">TRACE Naija</channel>
  <channel site="dstv.com" lang="en" xmltv_id="" site_id="eri#326">AFRO Music English</channel>
  <channel site="dstv.com" lang="en" xmltv_id="" site_id="eri#327">Sound City</channel>
  <channel site="dstv.com" lang="en" xmltv_id="" site_id="eri#330">QWEST TV</channel>
  <channel site="dstv.com" lang="en" xmltv_id="" site_id="eri#332">Trace Gospel</channel>
  <channel site="dstv.com" lang="en" xmltv_id="" site_id="eri#333">Trace Jama</channel>
  <channel site="dstv.com" lang="en" xmltv_id="" site_id="eri#334">TRACE Muzika</channel>
  <channel site="dstv.com" lang="en" xmltv_id="" site_id="eri#341">FAITH</channel>
  <channel site="dstv.com" lang="en" xmltv_id="" site_id="eri#342">Day Star</channel>
  <channel site="dstv.com" lang="en" xmltv_id="" site_id="eri#343">TBN</channel>
  <channel site="dstv.com" lang="en" xmltv_id="" site_id="eri#345">SBN</channel>
  <channel site="dstv.com" lang="en" xmltv_id="" site_id="eri#347">ISLAM CHANNEL</channel>
  <channel site="dstv.com" lang="en" xmltv_id="" site_id="eri#348">Eternal Word Television Network</channel>
  <channel site="dstv.com" lang="en" xmltv_id="" site_id="eri#349">Dove TV</channel>
  <channel site="dstv.com" lang="en" xmltv_id="" site_id="eri#363">Citi TV</channel>
  <channel site="dstv.com" lang="en" xmltv_id="" site_id="eri#364">Dominion TV</channel>
  <channel site="dstv.com" lang="en" xmltv_id="" site_id="eri#390">Emmanuel TV</channel>
  <channel site="dstv.com" lang="en" xmltv_id="" site_id="eri#400">BBC World News</channel>
  <channel site="dstv.com" lang="en" xmltv_id="" site_id="eri#401">CNN International</channel>
  <channel site="dstv.com" lang="en" xmltv_id="" site_id="eri#402">Sky News</channel>
  <channel site="dstv.com" lang="en" xmltv_id="" site_id="eri#404">SABC News</channel>
  <channel site="dstv.com" lang="en" xmltv_id="" site_id="eri#405">Newzroom Afrika</channel>
  <channel site="dstv.com" lang="en" xmltv_id="" site_id="eri#406">Al Jazeera</channel>
  <channel site="dstv.com" lang="en" xmltv_id="" site_id="eri#408">Plus TV Africa</channel>
  <channel site="dstv.com" lang="en" xmltv_id="" site_id="eri#409">CGTN News</channel>
  <channel site="dstv.com" lang="en" xmltv_id="" site_id="eri#410">CNBC Africa</channel>
  <channel site="dstv.com" lang="en" xmltv_id="" site_id="eri#411">Bloomberg Television</channel>
  <channel site="dstv.com" lang="en" xmltv_id="" site_id="eri#413">NDTV 24x7</channel>
  <channel site="dstv.com" lang="en" xmltv_id="" site_id="eri#414">EuroNews</channel>
  <channel site="dstv.com" lang="en" xmltv_id="" site_id="eri#416">Arise News</channel>
  <channel site="dstv.com" lang="en" xmltv_id="" site_id="eri#417">Africanews</channel>
  <channel site="dstv.com" lang="en" xmltv_id="" site_id="eri#421">Joy News</channel>
  <channel site="dstv.com" lang="en" xmltv_id="" site_id="eri#430">RAI International</channel>
  <channel site="dstv.com" lang="en" xmltv_id="" site_id="eri#431">NHK</channel>
  <channel site="dstv.com" lang="en" xmltv_id="" site_id="eri#437">TV5 Monde Afrique</channel>
  <channel site="dstv.com" lang="en" xmltv_id="" site_id="eri#438">EuroNews French</channel>
  <channel site="dstv.com" lang="en" xmltv_id="" site_id="eri#445">EuroNews German</channel>
  <channel site="dstv.com" lang="en" xmltv_id="" site_id="eri#446">Deutsche Welle</channel>
  <channel site="dstv.com" lang="en" xmltv_id="" site_id="eri#447">CCTV 4</channel>
  <channel site="dstv.com" lang="en" xmltv_id="" site_id="eri#449">CGTN French</channel>
  <channel site="dstv.com" lang="en" xmltv_id="" site_id="eri#451">B4U Movies</channel>
  <channel site="dstv.com" lang="en" xmltv_id="" site_id="eri#489">Maaddii Abol</channel>
  <channel site="dstv.com" lang="en" xmltv_id="" site_id="eri#525">RTPi (P)</channel>
  <channel site="dstv.com" lang="en" xmltv_id="" site_id="eri#680">TV Mundial (P)</channel>
  <channel site="dstv.com" lang="en" xmltv_id="" site_id="eri#720">Canal+</channel>
  <channel site="dstv.com" lang="en" xmltv_id="" site_id="eri#721">Canal+ Cinema Centre</channel>
  <channel site="dstv.com" lang="en" xmltv_id="" site_id="eri#722">Novelas TV</channel>
  <channel site="dstv.com" lang="en" xmltv_id="" site_id="eri#723">Canal+ Sports 2</channel>
  <channel site="dstv.com" lang="en" xmltv_id="" site_id="eri#724">Canal+ Sports 3</channel>
  <channel site="dstv.com" lang="en" xmltv_id="" site_id="eri#726">InfoSports+</channel>
  <channel site="dstv.com" lang="en" xmltv_id="" site_id="eri#727">TF1</channel>
  <channel site="dstv.com" lang="en" xmltv_id="" site_id="eri#728">France 2</channel>
  <channel site="dstv.com" lang="en" xmltv_id="" site_id="eri#729">A+</channel>
  <channel site="dstv.com" lang="en" xmltv_id="" site_id="eri#732">RTL 9</channel>
  <channel site="dstv.com" lang="en" xmltv_id="" site_id="eri#735">Trace Africa French</channel>
  <channel site="dstv.com" lang="en" xmltv_id="" site_id="eri#736">FRANCE 24</channel>
  <channel site="dstv.com" lang="en" xmltv_id="" site_id="eri#740">Planete</channel>
  <channel site="dstv.com" lang="en" xmltv_id="" site_id="eri#744">Teletoon+</channel>
  <channel site="dstv.com" lang="en" xmltv_id="" site_id="eri#745">Piwi+</channel>
</channels>
