<?xml version="1.0" encoding="UTF-8"?>
<site generator-info-name="WebGrab+Plus/w MDB &amp; REX Postprocess -- version V2.1.2 -- Jan van Straaten" site="7tv.de">
  <channels>
    <channel update="i" site="7tv.de" site_id="pro7" xmltv_id="ProSieben">ProSieben</channel>
    <channel update="i" site="7tv.de" site_id="sat1" xmltv_id="Sat.1">Sat.1</channel>
    <channel update="i" site="7tv.de" site_id="pro7maxx" xmltv_id="ProSieben Maxx">ProSieben Maxx</channel>
    <channel update="i" site="7tv.de" site_id="kabel1" xmltv_id="Kabeleins">Kabeleins</channel>
    <channel update="i" site="7tv.de" site_id="kabeleinsdoku" xmltv_id="Kabeleinsdoku">Kabeleinsdoku</channel>
    <channel update="i" site="7tv.de" site_id="sixx" xmltv_id="SIXX">SIXX</channel>
    <channel update="i" site="7tv.de" site_id="sat1gold" xmltv_id="Sat.1 Gold">Sat.1 Gold</channel>
    <channel update="i" site="7tv.de" site_id="puls8" xmltv_id="Puls8">Puls8</channel>
    <channel update="i" site="7tv.de" site_id="puls4" xmltv_id="Puls4">Puls4</channel>
  </channels>
</site>